{
  "Restorent": [
    {
      "id": 1,
      "name": "ASHISH",
      "address": "kanpur"
    },
    {
      "id": 2,
      "name": "deepa",
      "address": "kanpur"
    },
    {
      "id": 3,
      "name": "raju",
      "address": "kanpur"
    },
    {
      "id": 4,
      "name": "shah",
      "address": "kanpur"
    },
    {
      "id": 5,
      "name": "jcm",
      "address": "kanpur"
    },
    {
      "id": 6,
      "name": "jcm",
      "address": "kanpur"
    },
    {
      "id": 7,
      "name": "jamom",
      "address": "kannur"
    }
  ]
}